cwlupgrader/__init__.py
cwlupgrader/main.py
cwlupgrader/py.typed
cwlupgrader/testdata/draft-3/attributor-prok-cheetah.cwl
cwlupgrader/testdata/draft-3/wf.cwl
cwlupgrader/testdata/v1.0/1st-workflow.cwl
cwlupgrader/testdata/v1.0/arguments.cwl
cwlupgrader/testdata/v1.0/attributor-prok-cheetah.cwl
cwlupgrader/testdata/v1.0/conflict-wf.cwl
cwlupgrader/testdata/v1.0/listing_deep1-arr.cwl
cwlupgrader/testdata/v1.0/listing_deep1.cwl
cwlupgrader/testdata/v1.0/networkaccess.cwl
cwlupgrader/testdata/v1.0/tar-param.cwl
cwlupgrader/testdata/v1.0/wf.cwl
cwlupgrader/testdata/v1.1/conflict-wf.cwl
cwlupgrader/testdata/v1.1/listing_deep1-arr.cwl
cwlupgrader/testdata/v1.1/listing_deep1.cwl
cwlupgrader/testdata/v1.1/networkaccess.cwl
cwlupgrader/testdata/v1.2/1st-workflow.cwl
cwlupgrader/testdata/v1.2/arguments.cwl
cwlupgrader/testdata/v1.2/listing_deep1.cwl
cwlupgrader/testdata/v1.2/networkaccess.cwl
cwlupgrader/testdata/v1.2/tar-param.cwl
cwlupgrader/tests/__init__.py
cwlupgrader/tests/test_complete.py
cwlupgrader/tests/test_output_dir.py
cwlupgrader/tests/util.py
cwl_upgrader-1.2.11.dist-info/LICENSE.txt
cwl_upgrader-1.2.11.dist-info/METADATA
cwl_upgrader-1.2.11.dist-info/WHEEL
cwl_upgrader-1.2.11.dist-info/entry_points.txt
cwl_upgrader-1.2.11.dist-info/top_level.txt
cwl_upgrader-1.2.11.dist-info/zip-safe
cwl_upgrader-1.2.11.dist-info/RECORD
