Metadata-Version: 2.1
Name: cwl-upgrader
Version: 1.2.11
Summary: Upgrade a CWL tool or workflow document from one version to another
Author-email: Common Workflow Language project contributors <common-workflow-language@googlegroups.com>
License: Apache 2.0
Project-URL: Homepage, https://www.commonwl.org
Project-URL: Repository, https://github.com/common-workflow-language/cwl-upgrader
Project-URL: Issues, https://github.com/common-workflow-language/cwl-upgrader/issues
Project-URL: Changelog, https://github.com/common-workflow-language/cwl-upgrader/releases
Project-URL: Related Tools, https://www.commonwl.org/tools/
Keywords: cwl,commonwl,common-workflow-language
Classifier: Development Status :: 5 - Production/Stable
Classifier: Environment :: Console
Classifier: Intended Audience :: Developers
Classifier: License :: OSI Approved :: Apache Software License
Classifier: Operating System :: POSIX
Classifier: Operating System :: MacOS :: MacOS X
Classifier: Programming Language :: Python
Classifier: Programming Language :: Python :: 3
Classifier: Programming Language :: Python :: 3.8
Classifier: Programming Language :: Python :: 3.9
Classifier: Programming Language :: Python :: 3.10
Classifier: Programming Language :: Python :: 3.11
Classifier: Programming Language :: Python :: 3.12
Classifier: Topic :: File Formats
Classifier: Topic :: Software Development :: Libraries
Classifier: Typing :: Typed
Requires-Python: >=3.8
License-File: LICENSE.txt
Requires-Dist: setuptools
Requires-Dist: ruamel.yaml<0.19,>=0.16.0
Requires-Dist: schema_salad
Provides-Extra: testing
Requires-Dist: pytest<8; extra == "testing"
